{
  "type" : "sampler",
  "arguments" : {
    "type" : "cacheOnce",
    "arguments" : {
      "value" : {
        "type": "mul",
        "arguments": {
          "left": {
            "type": "add",
            "arguments": {
              "left": {
                "type": "mul",
                "arguments": {
                  "left": 2,
                  "right": {
                    "type": "noise",
                    "arguments": {
                      "noise": "Pillar",
                      "xzScale": 25,
                      "yScale": 0.3
                    }
                  }
                }
              },
              "right": {
                "type": "add",
                "arguments": {
                  "left": -1,
                  "right": {
                    "type": "mul",
                    "arguments": {
                      "left": -1,
                      "right": {
                        "type": "noise",
                        "arguments": {
                          "noise": "PillarRareness",
                          "xzScale": 1,
                          "yScale": 1
                        }
                      }
                    }
                  }
                }
              }
            }
          },
          "right": {
            "type": "cube",
            "arguments": {
              "value": {
                "type": "add",
                "arguments": {
                  "left": 0.55,
                  "right": {
                    "type": "mul",
                    "arguments": {
                      "left": 0.55,
                      "right": {
                        "type": "noise",
                        "arguments": {
                          "noise": "PillarThickness",
                          "xzScale": 1,
                          "yScale": 1
                        }
                      }
                    }
                  }
                }
              }
            }
          }
        }
      }
    }
  }
}